LICENSE
README.md
setup.cfg
setup.py
pbsc/__init__.py
pbsc.egg-info/PKG-INFO
pbsc.egg-info/SOURCES.txt
pbsc.egg-info/dependency_links.txt
pbsc.egg-info/entry_points.txt
pbsc.egg-info/requires.txt
pbsc.egg-info/top_level.txt