Metadata-Version: 2.1
Name: pbsc
Version: 0.1.0
Summary: High-Level API Client for Public Bike System Company
Home-page: https://github.com/officeofperformancemanagement/pbsc
Download-URL: https://github.com/officeofperformancemanagement/pbsc/tarball/download
Author: Daniel J. Dufour
Author-email: daniel.j.dufour@gmail.com
Keywords: data,python
Classifier: Development Status :: 4 - Beta
Classifier: Programming Language :: Python :: 3
Classifier: License :: CC0 1.0 Universal (CC0 1.0) Public Domain Dedication
Classifier: Operating System :: OS Independent
License-File: LICENSE
Requires-Dist: requests
